nautilus_librarian/__main__.py
nautilus_librarian/_helpers.py
nautilus_librarian/_version.py
nautilus_librarian/domain/dvc_diff_media_parser.py
nautilus_librarian/domain/dvc_services_api.py
nautilus_librarian/domain/file_locator.py
nautilus_librarian/domain/validate_filepaths.py
nautilus_librarian/main.py
nautilus_librarian/mods/console/domain/utils.py
nautilus_librarian/mods/dvc/domain/api.py
nautilus_librarian/mods/dvc/domain/diff/parser.py
nautilus_librarian/mods/dvc/domain/diff/path.py
nautilus_librarian/mods/dvc/domain/diff/path_list.py
nautilus_librarian/mods/dvc/domain/diff/renamed_path.py
nautilus_librarian/mods/dvc/domain/diff/renamed_path_list.py
nautilus_librarian/mods/dvc/domain/dvc_command_wrapper.py
nautilus_librarian/mods/dvc/domain/utils.py
nautilus_librarian/mods/dvc/typer/commands.py
nautilus_librarian/mods/filesystem/domain/absolute_filepath.py
nautilus_librarian/mods/filesystem/domain/directory.py
nautilus_librarian/mods/filesystem/domain/filename.py
nautilus_librarian/mods/filesystem/domain/filepath.py
nautilus_librarian/mods/filesystem/domain/relative_filepath.py
nautilus_librarian/mods/git/domain/git_command_wrapper.py
nautilus_librarian/mods/git/domain/git_user.py
nautilus_librarian/mods/git/domain/repo.py
nautilus_librarian/mods/git/domain/utils.py
nautilus_librarian/mods/git/typer/commands.py
nautilus_librarian/mods/gpg/domain/exceptions.py
nautilus_librarian/mods/gpg/domain/gpg_colon_list_parser.py
nautilus_librarian/mods/gpg/domain/gpg_command_wrapper.py
nautilus_librarian/mods/gpg/domain/gpg_connect_agent_wrapper.py
nautilus_librarian/mods/gpg/domain/services.py
nautilus_librarian/mods/gpg/domain/utils.py
nautilus_librarian/mods/gpg/domain/validation.py
nautilus_librarian/mods/gpg/typer/commands.py
nautilus_librarian/mods/libvips/domain/process_image.py
nautilus_librarian/mods/libvips/domain/utils.py
nautilus_librarian/mods/libvips/domain/validate_image_dimensions.py
nautilus_librarian/mods/libvips/typer/commands.py
nautilus_librarian-0.4.0.dist-info/entry_points.txt
nautilus_librarian-0.4.0.dist-info/LICENSE
nautilus_librarian-0.4.0.dist-info/WHEEL
nautilus_librarian-0.4.0.dist-info/METADATA
nautilus_librarian-0.4.0.dist-info/RECORD
