Metadata-Version: 2.1
Name: nautilus-librarian
Version: 0.4.0
Summary: A Python Console application to handle media libraries like Git and DVC
Home-page: https://github.com/Nautilus-Cyberneering/nautilus-librarian
Author: Jose Celano
Author-email: jose@nautilus-cyberneering.de
Maintainer: Jose Celano
Maintainer-email: jose@nautilus-cyberneering.de
Requires-Python: >=3.9,<4.0
Classifier: Development Status :: 1 - Planning
Classifier: Natural Language :: English
Classifier: Operating System :: POSIX
Classifier: Programming Language :: Python :: 3
Classifier: Programming Language :: Python :: 3.10
Classifier: Programming Language :: Python :: 3.9
Requires-Dist: Deprecated (>=1.2.13,<2.0.0)
Requires-Dist: GitPython (>=3.1.24)
Requires-Dist: PyGithub (>=1.55)
Requires-Dist: atoml (>=1.1.1,<2.0.0)
Requires-Dist: click (==8.0.4)
Requires-Dist: dvc[azure] (>=2.8.3,<3.0.0)
Requires-Dist: mypy (>=0.910,<0.911)
Requires-Dist: python-gnupg (>=0.4.8,<0.5.0)
Requires-Dist: pyvips (>=2.1.16)
Requires-Dist: typer[all] (>=0.4.0,<0.5.0)
Project-URL: Repository, https://github.com/Nautilus-Cyberneering/nautilus-librarian
